terraforge/__init__.py
terraforge/core.py
terraforge/utils.py
tests/__init__.py
tests/test_terraforge.py
terraforge-0.1.0.dist-info/LICENSE
terraforge-0.1.0.dist-info/METADATA
terraforge-0.1.0.dist-info/WHEEL
terraforge-0.1.0.dist-info/top_level.txt
terraforge-0.1.0.dist-info/RECORD
