Metadata-Version: 2.2
Name: TerraForge
Version: 0.1.0
Summary: A library for generating and manipulating Terraform configurations in HCL format.
Home-page: https://github.com/Elmo33/terraforge
Author: Saba Momtselidze
Author-email: sabamomtselidze@gmail.com
License: Apache License 2.0
Classifier: Programming Language :: Python :: 3
Classifier: License :: OSI Approved :: Apache Software License
Classifier: Operating System :: OS Independent
Requires-Python: >=3.6
License-File: LICENSE
Dynamic: author
Dynamic: author-email
Dynamic: classifier
Dynamic: description
Dynamic: description-content-type
Dynamic: home-page
Dynamic: license
Dynamic: requires-python
Dynamic: summary
